{
  "name": "Eyüp IŞIK",
  "title": "Sr. Frontend Developer, Vue.js",
  "birth": "December 16, 1995",
  "address": "Sultangazi, Istanbul, Turkey",
  "tel": "+90 537 871 2166",
  "mail": "hello@eisdev.me",
  "about": {
    "skills": [
      "HTML5",
      "CSS3",
      "SASS",
      "SCSS",
      "Less.js",
      "Bootstrap",
      "JS",
      "ES6+",
      "Node.js",
      "Express.js",
      "Vue.js",
      "VueNative",
      "Nuxt",
      "SSR",
      "RESTful API",
      "jQuery",
      "AJAX",
      "Axios",
      "Socket.io",
      "MongoDB",
      "MySQL",
      "PHP",
      "OOP",
      "Laravel"
    ],
    "intro": "I am a software developer who has {year} years of professional experience in Frontend &amp; PHP projects.",
    "closing": "As a programmer who is keen on innovations and willing to learn by using my knowledge and experience; I want to develop new projects with contemporary technologies.",
    "skillsText": "Powerful experiences on;",
    "items": [
      "UI Responsive, Cross-Browser Testing and UI/UX knowledge and experiences.",
      "Experienced in frontend development in; Asp.Net, Java, PHP sub-based applications.",
      "Knowledgeable in; Adobe Photoshop, Adobe XD, Adobe Illustrator and Zeplin.",
      "Numerous coding with different IDEs such as; JetBrains Products, VS Code, Notepad++, etc.",
      "Git, Agile &amp; Scrum."
    ]
  },
  "military": "Postponed to 2024",
  "works": [
    {
      "name": "Kodio app",
      "title": "Sr. Frontend Dev.",
      "time": "07.2020 – now"
    },
    {
      "name": "Koç Uni. Hospital",
      "title": "Sr. Frontend Dev.",
      "time": "02.2020 – 07.2020"
    },
    {
      "name": "Alegra",
      "title": "PHP Developer",
      "time": "09.2019 – 12.2019"
    },
    {
      "name": "Leox Tech.",
      "title": "Sr. Frontend Dev.",
      "time": "02.2018 – 07.2019"
    },
    {
      "name": "ajans123",
      "title": "Founder, FS Dev.",
      "time": "06.2016 – 02.2018"
    },
    {
      "name": "Webyayim",
      "title": "Full Stack Dev.",
      "time": "08.2014 – 04.2016"
    },
    {
      "name": "Marmara ajans",
      "title": "Full Stack Dev.",
      "time": "06.2013 – 08.2014"
    }
  ],
  "education": [
    {
      "name": "Web Design and Coding",
      "info": "Anadolu Uni. 2020 – now"
    },
    {
      "name": "Radio and TV Prog. Prod.",
      "info": "Anadolu Uni. 2015 – 2019"
    }
  ],
  "languages": [
    {
      "name": "Turkish",
      "degree": "native"
    },
    {
      "name": "English",
      "degree": "intermediate"
    }
  ]
}
